tinycov/__init__.py
tinycov/__main__.py
tinycov/tinycov.py
tinycov/utils.py
tinycov/version.py
tinycov-0.4.0.dist-info/LICENSE
tinycov-0.4.0.dist-info/METADATA
tinycov-0.4.0.dist-info/WHEEL
tinycov-0.4.0.dist-info/entry_points.txt
tinycov-0.4.0.dist-info/top_level.txt
tinycov-0.4.0.dist-info/RECORD
