Metadata-Version: 2.1
Name: tinycov
Version: 0.4.0
Summary: Standalone command line tool to visualize coverage from a BAM file
Home-page: https://github.com/cmdoret/tinycov
Author: cmdoret
Author-email: cyril.matthey-doret@pasteur.fr
License: MIT
Classifier: Development Status :: 3 - Alpha
Classifier: Intended Audience :: Science/Research
Classifier: Intended Audience :: Science/Research
Classifier: License :: OSI Approved :: MIT License
Classifier: Programming Language :: Python
Classifier: Programming Language :: Python :: 3
Classifier: Programming Language :: Python :: 3 :: Only
Classifier: Programming Language :: Python :: 3.6
Classifier: Programming Language :: Python :: 3.7
Classifier: Topic :: Scientific/Engineering
Classifier: Topic :: Scientific/Engineering :: Bio-Informatics
Classifier: Topic :: Scientific/Engineering :: Visualization
Classifier: Operating System :: Microsoft :: Windows
Classifier: Operating System :: POSIX
Classifier: Operating System :: Unix
Classifier: Operating System :: MacOS
Requires-Python: >=3.6
License-File: LICENSE
Requires-Dist: click (>=8.1.3)
Requires-Dist: colorama (>=0.4.6)
Requires-Dist: matplotlib (>=3.6.2)
Requires-Dist: numpy (>=1.23.5)
Requires-Dist: pandas (>=1.5.2)
Requires-Dist: pysam (>=0.20.0)
Requires-Dist: seaborn (>=0.12.1)
Requires-Dist: tqdm (>=4.64.1)
